pyfers/__init__.py
pyfers/fers.py
pyfers-1.2.2.dist-info/METADATA
pyfers-1.2.2.dist-info/WHEEL
pyfers-1.2.2.dist-info/top_level.txt
pyfers-1.2.2.dist-info/RECORD
